Lab 7/controlLogic.v
module controlLogic(opcode,state,PCWrite,PCWriteCond,IorD,MemRead,MemWrite,IRWrite,MemtoReg,PCSrc,AluOp,AluSrcA,AluSrcB,RegWrite,RegDst,nextState);
	input [5:0] opcode;
	input [3:0] state;
	output PCWrite,PCWriteCond,IorD,MemRead,MemWrite,IRWrite,MemtoReg,AluSrcA,RegWrite,RegDst;
	output [1:0] PCSrc,AluOp,AluSrcB;
	output [3:0] nextState;
	assign PCWrite=((~state[3])&(~state[2])&(~state[1])&(~state[0]))|((state[3])&(~state[2])&(~state[1])&(state[0]));
	assign PCWriteCond=((state[3])&(~state[2])&(~state[1])&(~state[0]));
	assign IorD=((~state[3])&(~state[2])&(state[1])&(state[0]))|((~state[3])&(state[2])&(~state[1])&(state[0]));
	assign MemRead=((~state[3])&(~state[2])&(~state[1])&(~state[0]))|((~state[3])&(~state[2])&(state[1])&(state[0]));
	assign MemWrite=((~state[3])&(state[2])&(~state[1])&(state[0]));
	assign IRWrite=((~state[3])&(~state[2])&(~state[1])&(~state[0]));
	assign MemtoReg=((~state[3])&(state[2])&(~state[1])&(~state[0]));
	assign PCSrc[1]=((state[3])&(~state[2])&(~state[1])&(state[0]));
	assign PCSrc[0]=((state[3])&(~state[2])&(~state[1])&(~state[0]));
	assign AluOp[1]=((~state[3])&(state[2])&(state[1])&(~state[0]));
	assign AluOp[0]=((state[3])&(~state[2])&(~state[1])&(~state[0]));
	assign AluSrcB[1]=((~state[3])&(~state[2])&(~state[1])&(state[0]))|((~state[3])&(~state[2])&(state[1])&(~state[0]));
	assign AluSrcB[0]=((~state[3])&(~state[2])&(~state[1])&(~state[0]))|((~state[3])&(~state[2])&(~state[1])&(state[0]));
	assign AluSrcA=((~state[3])&(~state[2])&(state[1])&(~state[0]))|((~state[3])&(state[2])&(state[1])&(~state[0]))|((state[3])&(~state[2])&(~state[1])&(~state[0]));
	assign RegWrite=((~state[3])&(state[2])&(~state[1])&(~state[0]))|((~state[3])&(state[2])&(state[1])&(state[0]));
	assign RegDst=((~state[3])&(state[2])&(state[1])&(state[0]));
	assign nextState[3]=((~opcode[5])&(~opcode[4])&(~opcode[3])&(~opcode[2])&(opcode[1])&(~opcode[0])&(~state[3])&(~state[2])&(~state[1])&(state[0]))|((~opcode[5])&(~opcode[4])&(~opcode[3])&(opcode[2])&(~opcode[1])&(~opcode[0])&(~state[3])&(~state[2])&(~state[1])&(state[0]));
	assign nextState[2]=((~state[3])&(~state[2])&(state[1])&(state[0]))|((~state[3])&(state[2])&(state[1])&(~state[0]))|((~opcode[5])&(~opcode[4])&(~opcode[3])&(~opcode[2])&(~opcode[1])&(~opcode[0])&(~state[3])&(~state[2])&(~state[1])&(state[0]))|((opcode[5])&(~opcode[4])&(opcode[3])&(~opcode[2])&(opcode[1])&(opcode[0])&(~state[3])&(~state[2])&(state[1])&(~state[0]));
	assign nextState[1]=((~state[3])&(state[2])&(state[1])&(~state[0]))|((~opcode[5])&(~opcode[4])&(~opcode[3])&(~opcode[2])&(~opcode[1])&(~opcode[0])&(~state[3])&(~state[2])&(~state[1])&(state[0]))|((opcode[5])&(~opcode[4])&(~opcode[3])&(~opcode[2])&(opcode[1])&(opcode[0])&(~state[3])&(~state[2])&(state[1])&(~state[0]))|((opcode[5])&(~opcode[4])&(opcode[3])&(~opcode[2])&(opcode[1])&(opcode[0])&(~state[3])&(~state[2])&(~state[1])&(state[0]))|((opcode[5])&(~opcode[4])&(~opcode[3])&(~opcode[2])&(opcode[1])&(opcode[0])&(~state[3])&(~state[2])&(~state[1])&(state[0]));
	assign nextState[0]=((~state[3])&(~state[2])&(~state[1])&(~state[0]))|((~state[3])&(state[2])&(state[1])&(~state[0]))|((~opcode[5])&(~opcode[4])&(~opcode[3])&(~opcode[2])&(opcode[1])&(~opcode[0])&(~state[3])&(~state[2])&(~state[1])&(state[0]))|((opcode[5])&(~opcode[4])&(opcode[3])&(~opcode[2])&(opcode[1])&(opcode[0])&(~state[3])&(~state[2])&(state[1])&(~state[0]))|((opcode[5])&(~opcode[4])&(~opcode[3])&(~opcode[2])&(opcode[1])&(opcode[0])&(~state[3])&(~state[2])&(state[1])&(~state[0]));
endmodule

Lab 7/stateReg.v
module reg4Bit(in,clk,out);
	input [3:0] in;
	input clk;
	output reg [3:0] out;
	initial
	begin
		out<=4'b0000;
	end
	always@(negedge clk)
	begin
		out<=in;
	end
endmodule

Lab 7/controller.v
`include "controlLogic.v"
`include "stateReg.v"
module multicycleController(clk,opcode,PCWrite,PCWriteCond,IorD,MemRead,MemWrite,IRWrite,MemtoReg,PCSrc,AluOp,AluSrcA,AluSrcB,RegWrite,RegDst);
	input [5:0] opcode;
	input clk;
	output PCWrite,PCWriteCond,IorD,MemRead,MemWrite,IRWrite,MemtoReg,AluSrcA,RegWrite,RegDst;
	output [1:0] PCSrc,AluOp,AluSrcB;
	wire [3:0] curr,next;
	reg4Bit r1(next,clk,curr);
	controlLogic cl(opcode,curr,PCWrite,PCWriteCond,IorD,MemRead,MemWrite,IRWrite,MemtoReg,PCSrc,AluOp,AluSrcA,AluSrcB,RegWrite,RegDst,next);
endmodule

module tb_control;
	reg [5:0] opcode;
	reg clk;
	wire PCWrite,PCWriteCond,IorD,MemRead,MemWrite,IRWrite,MemtoReg,AluSrcA,RegWrite,RegDst;
	wire [1:0] PCSrc,AluOp,AluSrcB;
	multicycleController mcc(clk,opcode,PCWrite,PCWriteCond,IorD,MemRead,MemWrite,IRWrite,MemtoReg,PCSrc,AluOp,AluSrcA,AluSrcB,RegWrite,RegDst);
	always@(clk)
	begin
		#10 clk<=~clk;
	end
	initial 
	begin
		clk=1'b1;opcode=6'b100011;//lw
		$dumpfile("controller.vcd");$dumpvars();
		$monitor("opcode=%b, PCWrite=%b, PCWriteCond=%b, IorD=%b, MemRead=%b, MemWrite=%b, IRWrite=%b, MemtoReg=%b, PCSrc=%b, AluOp=%b, AluSrcA=%b, AluSrcB=%b, RegWrite=%b, RegDst=%b",opcode,PCWrite,PCWriteCond,IorD,MemRead,MemWrite,IRWrite,MemtoReg,PCSrc,AluOp,AluSrcA,AluSrcB,RegWrite,RegDst);
		#200 $finish;
	end
endmodule

Lab 7/controller.vcd
$date
	Thu Oct 15 17:43:08 2020
$end
$version
	Icarus Verilog
$end
$timescale
	1s
$end
$scope module tb_control $end
$var wire 1 ! RegWrite $end
$var wire 1 " RegDst $end
$var wire 1 # PCWriteCond $end
$var wire 1 $ PCWrite $end
$var wire 2 % PCSrc [1:0] $end
$var wire 1 & MemtoReg $end
$var wire 1 ' MemWrite $end
$var wire 1 ( MemRead $end
$var wire 1 ) IorD $end
$var wire 1 * IRWrite $end
$var wire 2 + AluSrcB [1:0] $end
$var wire 1 , AluSrcA $end
$var wire 2 - AluOp [1:0] $end
$var reg 1 . clk $end
$var reg 6 / opcode [5:0] $end
$scope module mcc $end
$var wire 1 . clk $end
$var wire 6 0 opcode [5:0] $end
$var wire 4 1 next [3:0] $end
$var wire 4 2 curr [3:0] $end
$var wire 1 ! RegWrite $end
$var wire 1 " RegDst $end
$var wire 1 # PCWriteCond $end
$var wire 1 $ PCWrite $end
$var wire 2 3 PCSrc [1:0] $end
$var wire 1 & MemtoReg $end
$var wire 1 ' MemWrite $end
$var wire 1 ( MemRead $end
$var wire 1 ) IorD $end
$var wire 1 * IRWrite $end
$var wire 2 4 AluSrcB [1:0] $end
$var wire 1 , AluSrcA $end
$var wire 2 5 AluOp [1:0] $end
$scope module cl $end
$var wire 1 , AluSrcA $end
$var wire 1 * IRWrite $end
$var wire 1 ) IorD $end
$var wire 1 ( MemRead $end
$var wire 1 ' MemWrite $end
$var wire 1 & MemtoReg $end
$var wire 1 $ PCWrite $end
$var wire 1 # PCWriteCond $end
$var wire 1 " RegDst $end
$var wire 1 ! RegWrite $end
$var wire 6 6 opcode [5:0] $end
$var wire 4 7 state [3:0] $end
$var wire 4 8 nextState [3:0] $end
$var wire 2 9 PCSrc [1:0] $end
$var wire 2 : AluSrcB [1:0] $end
$var wire 2 ; AluOp [1:0] $end
$upscope $end
$scope module r1 $end
$var wire 1 . clk $end
$var wire 4 < in [3:0] $end
$var reg 4 = out [3:0] $end
$upscope $end
$upscope $end
$upscope $end
$enddefinitions $end
#0
$dumpvars
b0 =
b1 <
b0 ;
b1 :
b0 9
b1 8
b0 7
b100011 6
b0 5
b1 4
b0 3
b0 2
b1 1
b100011 0
b100011 /
1.
b0 -
0,
b1 +
1*
0)
1(
0'
0&
b0 %
1$
0#
0"
0!
$end
#10
0(
0$
b10 1
b10 8
b10 <
b11 +
b11 4
b11 :
0*
b1 2
b1 7
b1 =
0.
#20
1.
#30
1,
b11 1
b11 8
b11 <
b10 +
b10 4
b10 :
b10 2
b10 7
b10 =
0.
#40
1.
#50
0,
b100 1
b100 8
b100 <
b0 +
b0 4
b0 :
1(
1)
b11 2
b11 7
b11 =
0.
#60
1.
#70
b0 1
b0 8
b0 <
1!
1&
0(
0)
b100 2
b100 7
b100 =
0.
#80
1.
#90
b1 1
b1 8
b1 <
b1 +
b1 4
b1 :
1(
1$
0!
1*
0&
b0 2
b0 7
b0 =
0.
#100
1.
#110
0(
0$
b10 1
b10 8
b10 <
b11 +
b11 4
b11 :
0*
b1 2
b1 7
b1 =
0.
#120
1.
#130
1,
b11 1
b11 8
b11 <
b10 +
b10 4
b10 :
b10 2
b10 7
b10 =
0.
#140
1.
#150
0,
b100 1
b100 8
b100 <
b0 +
b0 4
b0 :
1(
1)
b11 2
b11 7
b11 =
0.
#160
1.
#170
b0 1
b0 8
b0 <
1!
1&
0(
0)
b100 2
b100 7
b100 =
0.
#180
1.
#190
b1 1
b1 8
b1 <
b1 +
b1 4
b1 :
1(
1$
0!
1*
0&
b0 2
b0 7
b0 =
0.
