Lab 1/1BitFullAdder/adder1bit.v
module adder1bit(sum,carry,a,b);
	input a,b;
	output sum,carry;
	assign sum=a^b;
	assign carry=a&b;
endmodule

Lab 3/shift register adder/fa1bit.v
`include "adder1bit.v"
module fulladder1bit(sum,cout,a,b,cin);
	input a,b,cin;
	output sum,cout;
	wire s,c;
	adder1bit half_adder(s,c,a,b);
	//s=a^b
	//c=a&b
	assign sum=s^cin;
	assign cout=cin&s|c;
endmodule

Lab 1/4bitFullAdder/adder4bit.v
`include "fa1bit.v"
module adder4bit(sum,carry,a,b);
	input [3:0]a,b;
	output [3:0]sum;
	output carry;
	wire c0,c1,c2;
	fulladder1bit f1(sum[0],c0,a[0],b[0],1'b0);
	fulladder1bit f2(sum[1],c1,a[1],b[1],c0);
	fulladder1bit f3(sum[2],c2,a[2],b[2],c1);
	fulladder1bit f4(sum[3],carry,a[3],b[3],c2);
endmodule

Lab 1/4bitFullAdder/tb_4bit.v
`include "adder4bit.v"
module testbench;
	reg [3:0] a,b;
	wire [3:0]sum;
	wire carry;
	adder4bit a1(sum,carry,a,b);
	initial
		begin
			$dumpfile("output.vcd"); $dumpvars;
			$monitor(,$time," a=%b, b=%b, sum=%b, carry=%b",a,b,sum,carry);
			#0 a=4'b0000;b=4'b0000;
			#10 a=4'b0000;b=4'b1111;
			#20 a=4'b0000;b=4'b1010;
			#30 a=4'b0001;b=4'b1111;
			#40 a=4'b1111;b=4'b1111;
			#50 a=4'b0101;b=4'b1010;
			#60 a=4'b0011;b=4'b1100;
			#70 a=4'b1000;b=4'b1011;
			#80 $finish;
		end
endmodule

Lab 1/4bitFullAdder/output.vcd
$date
	Thu Aug 27 16:56:55 2020
$end
$version
	Icarus Verilog
$end
$timescale
	1s
$end
$scope module testbench $end
$var wire 4 ! sum [3:0] $end
$var wire 1 " carry $end
$var reg 4 # a [3:0] $end
$var reg 4 $ b [3:0] $end
$scope module a1 $end
$var wire 4 % a [3:0] $end
$var wire 4 & b [3:0] $end
$var wire 4 ' sum [3:0] $end
$var wire 1 " carry $end
$var wire 1 ( c2 $end
$var wire 1 ) c1 $end
$var wire 1 * c0 $end
$scope module f1 $end
$var wire 1 + a $end
$var wire 1 , b $end
$var wire 1 - cin $end
$var wire 1 * cout $end
$var wire 1 . sum $end
$var wire 1 / s $end
$var wire 1 0 c $end
$scope module half_adder $end
$var wire 1 + a $end
$var wire 1 , b $end
$var wire 1 0 carry $end
$var wire 1 / sum $end
$upscope $end
$upscope $end
$scope module f2 $end
$var wire 1 1 a $end
$var wire 1 2 b $end
$var wire 1 * cin $end
$var wire 1 ) cout $end
$var wire 1 3 sum $end
$var wire 1 4 s $end
$var wire 1 5 c $end
$scope module half_adder $end
$var wire 1 1 a $end
$var wire 1 2 b $end
$var wire 1 5 carry $end
$var wire 1 4 sum $end
$upscope $end
$upscope $end
$scope module f3 $end
$var wire 1 6 a $end
$var wire 1 7 b $end
$var wire 1 ) cin $end
$var wire 1 ( cout $end
$var wire 1 8 sum $end
$var wire 1 9 s $end
$var wire 1 : c $end
$scope module half_adder $end
$var wire 1 6 a $end
$var wire 1 7 b $end
$var wire 1 : carry $end
$var wire 1 9 sum $end
$upscope $end
$upscope $end
$scope module f4 $end
$var wire 1 ; a $end
$var wire 1 < b $end
$var wire 1 ( cin $end
$var wire 1 " cout $end
$var wire 1 = sum $end
$var wire 1 > s $end
$var wire 1 ? c $end
$scope module half_adder $end
$var wire 1 ; a $end
$var wire 1 < b $end
$var wire 1 ? carry $end
$var wire 1 > sum $end
$upscope $end
$upscope $end
$upscope $end
$upscope $end
$enddefinitions $end
#0
$dumpvars
0?
0>
0=
0<
0;
0:
09
08
07
06
05
04
03
02
01
00
0/
0.
0-
0,
0+
0*
0)
0(
b0 '
b0 &
b0 %
b0 $
b0 #
0"
b0 !
$end
#10
1.
13
18
b1111 !
b1111 '
1=
1/
14
19
1>
1,
12
17
1<
b1111 $
b1111 &
#30
0.
b1010 !
b1010 '
08
0/
09
0,
07
b1010 $
b1010 &
#60
1"
0=
1(
1)
03
b0 !
b0 '
08
1*
19
10
1,
17
1+
b1111 $
b1111 &
b1 #
b1 %
#100
13
18
b1110 !
b1110 '
1=
04
15
09
1:
0>
1?
11
16
1;
b1111 #
b1111 %
#150
18
1.
0*
0(
13
0)
b1111 !
b1111 '
1=
0"
1/
00
19
0:
14
05
1>
0?
0,
07
01
0;
b1010 $
b1010 &
b101 #
b101 %
#210
02
17
11
06
b1100 $
b1100 &
b11 #
b11 %
#280
08
b11 !
b11 '
0=
1"
09
0>
1?
1,
12
07
0+
01
1;
b1011 $
b1011 &
b1000 #
b1000 %
