Lab 2/mux16_1/mux4_1.v
module mux4_1(op,ip,s);
	output op;
	input [3:0] ip;
	input [1:0] s;
	assign op=(~s[0] & ~s[1] & ip[0])|(s[0] & ~s[1] & ip[1])|(~s[0] & s[1] & ip[2])|(s[0] & s[1] & ip[3]);
endmodule

Lab 2/mux16_1/mux16_1.v
`include "mux4_1.v"
module mux16_1(op,ip,s);
	input [15:0] ip;
	input [3:0] s;
	output op;
	wire [3:0]w;
	mux4_1 m1(w[0],ip[3:0],s[1:0]);
	mux4_1 m2(w[1],ip[7:4],s[1:0]);
	mux4_1 m3(w[2],ip[11:8],s[1:0]);
	mux4_1 m4(w[3],ip[15:12],s[1:0]);
	mux4_1 m5(op,w,s[3:2]);
endmodule

Lab 2/mux16_1/tb_mux16_1.v
`include "mux16_1.v"
module testbench;
	reg [15:0] in;
	reg [3:0] sel;
	wire out;
	mux16_1 m1(out,in,sel);
	initial
		begin
			$dumpfile("output.vcd");$dumpvars();
			$monitor("in=%b | sel=%b | out=%b",in,sel,out);
			#0 in=16'b1000000000000000; sel=4'b0000;
			#3 in=16'b1000000000000000; sel=4'b0001;
			#3 in=16'b1000000000000000; sel=4'b0010;
			#3 in=16'b1000000000000000; sel=4'b0011;
			#3 in=16'b1000000000000000; sel=4'b0100;
			#3 in=16'b1000000000000000; sel=4'b0101; 
			#3 in=16'b1000000000000000; sel=4'b0110; 
			#3 in=16'b1000000000000000; sel=4'b0111; 
			#3 in=16'b1000000000000000; sel=4'b1000; 
			#3 in=16'b1000000000000000; sel=4'b1001; 
			#3 in=16'b1000000000000000; sel=4'b1010; 
			#3 in=16'b1000000000000000; sel=4'b1011; 
			#3 in=16'b1000000000000000; sel=4'b1100;
			#3 in=16'b1000000000000000; sel=4'b1101;
			#3 in=16'b1000000000000000; sel=4'b1110; 
			#3 in=16'b1000000000000000; sel=4'b1111;
		end
endmodule

Lab 2/mux16_1/output.vcd
$date
	Thu Sep 03 14:52:14 2020
$end
$version
	Icarus Verilog
$end
$timescale
	1s
$end
$scope module testbench $end
$var wire 1 ! out $end
$var reg 16 " in [15:0] $end
$var reg 4 # sel [3:0] $end
$scope module m1 $end
$var wire 16 $ ip [15:0] $end
$var wire 4 % s [3:0] $end
$var wire 4 & w [3:0] $end
$var wire 1 ! op $end
$scope module m1 $end
$var wire 4 ' ip [3:0] $end
$var wire 1 ( op $end
$var wire 2 ) s [1:0] $end
$upscope $end
$scope module m2 $end
$var wire 4 * ip [3:0] $end
$var wire 1 + op $end
$var wire 2 , s [1:0] $end
$upscope $end
$scope module m3 $end
$var wire 4 - ip [3:0] $end
$var wire 1 . op $end
$var wire 2 / s [1:0] $end
$upscope $end
$scope module m4 $end
$var wire 4 0 ip [3:0] $end
$var wire 1 1 op $end
$var wire 2 2 s [1:0] $end
$upscope $end
$scope module m5 $end
$var wire 4 3 ip [3:0] $end
$var wire 1 ! op $end
$var wire 2 4 s [1:0] $end
$upscope $end
$upscope $end
$upscope $end
$enddefinitions $end
#0
$dumpvars
b0 4
b0 3
b0 2
01
b1000 0
b0 /
0.
b0 -
b0 ,
0+
b0 *
b0 )
0(
b0 '
b0 &
b0 %
b1000000000000000 $
b0 #
b1000000000000000 "
0!
$end
#3
b1 )
b1 ,
b1 /
b1 2
b1 #
b1 %
#6
b10 )
b10 ,
b10 /
b10 2
b10 #
b10 %
#9
b1000 &
b1000 3
11
b11 )
b11 ,
b11 /
b11 2
b11 #
b11 %
#12
b0 &
b0 3
01
b0 )
b0 ,
b0 /
b0 2
b1 4
b100 #
b100 %
#15
b1 )
b1 ,
b1 /
b1 2
b101 #
b101 %
#18
b10 )
b10 ,
b10 /
b10 2
b110 #
b110 %
#21
b1000 &
b1000 3
11
b11 )
b11 ,
b11 /
b11 2
b111 #
b111 %
#24
b0 &
b0 3
01
b0 )
b0 ,
b0 /
b0 2
b10 4
b1000 #
b1000 %
#27
b1 )
b1 ,
b1 /
b1 2
b1001 #
b1001 %
#30
b10 )
b10 ,
b10 /
b10 2
b1010 #
b1010 %
#33
b1000 &
b1000 3
11
b11 )
b11 ,
b11 /
b11 2
b1011 #
b1011 %
#36
b0 &
b0 3
01
0!
b0 )
b0 ,
b0 /
b0 2
b11 4
b1100 #
b1100 %
#39
b1 )
b1 ,
b1 /
b1 2
b1101 #
b1101 %
#42
b10 )
b10 ,
b10 /
b10 2
b1110 #
b1110 %
#45
1!
b1000 &
b1000 3
11
b11 )
b11 ,
b11 /
b11 2
b1111 #
b1111 %
