Lab 2/Adder from decoder/decoder.v
module decoder(op,ip);
	output [7:0] op;
	input [2:0] ip;
	//Gate level
	wire x1,y1,z1,w1;
	not n1(x1,ip[0]);
	not n2(y1,ip[1]);
	not n3(z1,ip[2]);
	and a0(op[0],z1,y1,x1);
	and a1(op[1],z1,y1,ip[0]);
	and a2(op[2],z1,ip[1],x1);
	and a3(op[3],z1,ip[1],ip[0]);
	and a4(op[4],ip[2],y1,x1);
	and a5(op[5],ip[2],y1,ip[0]);
	and a6(op[6],ip[2],ip[1],x1);
	and a7(op[7],ip[2],ip[1],ip[0]);
endmodule

Lab 2/Adder from decoder/fadder.v
`include "decoder.v"
module fadder(sum,carry,ip);
	input [2:0] ip;
	output sum,carry;
	wire [7:0] w;
	decoder d1(w,ip);
	or o1(sum,w[1],w[2],w[4],w[7]);
	or o2(carry,w[3],w[5],w[6],w[7]);
endmodule

Lab 2/Adder from decoder/tb_fadder.v
`include "fadder.v"
module testbench;
	reg [2:0] ip;
	wire s,c;
	fadder f1(s,c,ip);
	initial
		begin
			$dumpfile("ouput.vcd");$dumpvars();
			$monitor(,$time," input=%b,s=%b,c=%b",ip,s,c);
			#0 ip=3'b000;
			#4 ip=3'b100;
			#4 ip=3'b010;
			#4 ip=3'b110;
			#4 ip=3'b001;
			#4 ip=3'b101;
			#4 ip=3'b011;
			#4 ip=3'b111;
		end
endmodule

Lab 2/Adder from decoder/ouput.vcd
$date
	Thu Sep 03 15:17:33 2020
$end
$version
	Icarus Verilog
$end
$timescale
	1s
$end
$scope module testbench $end
$var wire 1 ! s $end
$var wire 1 " c $end
$var reg 3 # ip [2:0] $end
$scope module f1 $end
$var wire 1 " carry $end
$var wire 3 $ ip [2:0] $end
$var wire 1 ! sum $end
$var wire 8 % w [7:0] $end
$scope module d1 $end
$var wire 3 & ip [2:0] $end
$var wire 1 ' x1 $end
$var wire 1 ( y1 $end
$var wire 1 ) z1 $end
$var wire 8 * op [7:0] $end
$upscope $end
$upscope $end
$upscope $end
$enddefinitions $end
#0
$dumpvars
b1 *
1)
1(
1'
b0 &
b1 %
b0 $
b0 #
0"
0!
$end
#4
1!
0)
b10000 %
b10000 *
b100 #
b100 $
b100 &
#8
1!
0(
1)
b100 %
b100 *
b10 #
b10 $
b10 &
#12
0!
1"
0)
b1000000 %
b1000000 *
b110 #
b110 $
b110 &
#16
1!
0"
0'
1(
1)
b10 %
b10 *
b1 #
b1 $
b1 &
#20
0!
1"
0)
b100000 %
b100000 *
b101 #
b101 $
b101 &
#24
1"
0(
1)
b1000 %
b1000 *
b11 #
b11 $
b11 &
#28
1!
0)
b10000000 %
b10000000 *
b111 #
b111 $
b111 &
