Practice_test/prog.v
module REG1(clk,EN,numin,numout);
	input clk,EN;
	input [3:0] numin;
	output reg [3:0] numout;
	always@(posedge clk)
	begin
		if(EN) numout<=numin;
	end
endmodule

module ROTATOR(clk,Enable,numo,numrotated);
	input clk,Enable;
	input [3:0] numo;
	output reg [3:0] numrotated;
	always@(posedge clk)
	begin
		if(Enable) numrotated={numo[0],numo[3:1]};
	end
endmodule

module MULTIPLIER(op1,op2,product);
	input [3:0] op1,op2;
	output reg [7:0] product;
	reg [3:0] A,M,Q;
	reg C;
	integer count;
	always@(op1 or op2)
	begin
		count=4;
		A=4'b0000;
		M=op1;
		Q=op2;
		C=1'b0;
		while(count!=0)
		begin
			if(Q[0]==1)
			begin
				{C,A} = A+M;
			end
			{C,A,Q}={1'b0,C,A,Q[3:1]};
			count=count-1;
		end
		product <= {A,Q};
	end
endmodule

module DECODER(sel,out1);
	input [3:0] sel;
	output reg [15:0] out1;
	always@(sel)
	begin
		out1=16'd0;
		out1[sel]=1;
	end
endmodule

module MEMORY(WE,datatowrite,regsel,readdata);
	input WE;
	input [15:0] regsel;
	input [7:0] datatowrite;
	reg [7:0] mem [15:0];
	output reg [7:0] readdata;
	always@(WE or datatowrite or regsel)
	begin
		case(regsel)
				16'b0000_0000_0000_0001:begin
					if(WE) mem[0] = datatowrite;
					readdata = mem[0];
				end
				16'b0000_0000_0000_0010:begin
					if(WE) mem[1] = datatowrite;
					readdata = mem[1];
				end
				16'b0000_0000_0000_0100:begin
					if(WE) mem[2] = datatowrite;
					readdata = mem[2];
				end
				16'b0000_0000_0000_1000:begin
					if(WE) mem[3] = datatowrite;
					readdata = mem[3];
				end
				16'b0000_0000_0001_0000:begin
					if(WE) mem[4] = datatowrite;
					readdata = mem[4];
				end
				16'b0000_0000_0010_0000:begin
					if(WE) mem[5] = datatowrite;
					readdata = mem[5];
				end
				16'b0000_0000_0100_0000:begin
					if(WE) mem[6] = datatowrite;
					readdata = mem[6];
				end
				16'b0000_0000_1000_0000:begin
					if(WE) mem[7] = datatowrite;
					readdata = mem[7];
				end
				16'b0000_0001_0000_0000:begin
					if(WE) mem[8] = datatowrite;
					readdata = mem[8];
				end
				16'b0000_0010_0000_0000:begin
					if(WE) mem[9] = datatowrite;
					readdata = mem[9];
				end
				16'b0000_0100_0000_0000:begin
					if(WE) mem[10] = datatowrite;
					readdata = mem[10];
				end
				16'b0000_1000_0000_0000:begin
					if(WE) mem[11] = datatowrite;
					readdata = mem[11];
				end
				16'b0001_0000_0000_0000:begin
					if(WE) mem[12] = datatowrite;
					readdata = mem[12];
				end
				16'b0010_0000_0000_0000:begin
					if(WE) mem[13] = datatowrite;
					readdata = mem[13];
				end
				16'b0100_0000_0000_0000:begin
					if(WE) mem[14] = datatowrite;
					readdata = mem[14];
				end
				16'b1000_0000_0000_0000:begin
					if(WE) mem[15] = datatowrite;
					readdata = mem[15];
				end
		endcase
	end
endmodule
module DATAPATH(num,key,storedvalue);
	input [3:0] num,key;
	reg clk,EN,Enable,WE;
	wire [3:0] numo,numrot,numrot1;
	wire [7:0] prod;
	wire [15:0] addr;
	output [7:0] storedvalue;
	initial
	begin
		#0 clk=1'b1;EN=1'b1;Enable=1'b1;WE=1'b1;
	end
	always
	begin
		#5 clk=~clk;
	end
	REG1 reg1(clk,EN,num,numo);
	ROTATOR r1(clk,Enable,numo,numrot);
	ROTATOR r2(clk,Enable,numrot,numrot1);
	MULTIPLIER mult(numrot1,key,prod);
	DECODER dec(numo,addr);
	MEMORY m1(WE,prod,addr,storedvalue);
endmodule


module TESTBENCH;
	reg [3:0] num,key;
	wire [7:0] storedvalue;
	DATAPATH dp(num,key,storedvalue);
	initial
	begin
		$dumpfile("out.vcd");
		$dumpvars();
		$monitor($time," num=%b, key=%b, val=%b",num,key,storedvalue);
		#0 num=4'b1000;key=4'b1000;
		#12 num=4'b1001;key=4'b1000;
		#12 num=4'b1100;key=4'b1010;
		#12 num=4'b1011;key=4'b1110;
		#50 $finish;
	end
endmodule

Practice_test/out.vcd
$date
	Sat Nov 07 13:03:44 2020
$end
$version
	Icarus Verilog
$end
$timescale
	1s
$end
$scope module TESTBENCH $end
$var wire 8 ! storedvalue [7:0] $end
$var reg 4 " key [3:0] $end
$var reg 4 # num [3:0] $end
$scope module dp $end
$var wire 4 $ key [3:0] $end
$var wire 4 % num [3:0] $end
$var wire 8 & storedvalue [7:0] $end
$var wire 8 ' prod [7:0] $end
$var wire 4 ( numrot1 [3:0] $end
$var wire 4 ) numrot [3:0] $end
$var wire 4 * numo [3:0] $end
$var wire 16 + addr [15:0] $end
$var reg 1 , EN $end
$var reg 1 - Enable $end
$var reg 1 . WE $end
$var reg 1 / clk $end
$scope module dec $end
$var wire 4 0 sel [3:0] $end
$var reg 16 1 out1 [15:0] $end
$upscope $end
$scope module m1 $end
$var wire 1 . WE $end
$var wire 16 2 regsel [15:0] $end
$var wire 8 3 datatowrite [7:0] $end
$var reg 8 4 readdata [7:0] $end
$upscope $end
$scope module mult $end
$var wire 4 5 op2 [3:0] $end
$var wire 4 6 op1 [3:0] $end
$var reg 4 7 A [3:0] $end
$var reg 1 8 C $end
$var reg 4 9 M [3:0] $end
$var reg 4 : Q [3:0] $end
$var reg 8 ; product [7:0] $end
$var integer 32 < count [31:0] $end
$upscope $end
$scope module r1 $end
$var wire 1 - Enable $end
$var wire 1 / clk $end
$var wire 4 = numo [3:0] $end
$var reg 4 > numrotated [3:0] $end
$upscope $end
$scope module r2 $end
$var wire 1 - Enable $end
$var wire 1 / clk $end
$var wire 4 ? numo [3:0] $end
$var reg 4 @ numrotated [3:0] $end
$upscope $end
$scope module reg1 $end
$var wire 1 , EN $end
$var wire 1 / clk $end
$var wire 4 A numin [3:0] $end
$var reg 4 B numout [3:0] $end
$upscope $end
$upscope $end
$upscope $end
$enddefinitions $end
#0
$dumpvars
b1000 B
b1000 A
bx @
bx ?
bx >
b1000 =
b0 <
bx000 ;
bx000 :
bx 9
08
bx 7
bx 6
b1000 5
bx000 4
bx000 3
b100000000 2
b100000000 1
b1000 0
1/
1.
1-
1,
b100000000 +
b1000 *
bx )
bx (
bx000 '
bx000 &
b1000 %
b1000 $
b1000 #
b1000 "
bx000 !
$end
#5
0/
#10
b10000 !
b10000 &
b10000 4
b10000 '
b10000 3
b10000 ;
b0 :
b10 9
b1 7
b0 <
b10 (
b10 6
b10 @
b100 )
b100 >
b100 ?
1/
#12
b1001 #
b1001 %
b1001 A
#15
0/
#20
b1000000000 +
b1000000000 1
b1000000000 2
b1001 *
b1001 0
b1001 =
b1001 B
1/
#24
b10100 !
b10100 &
b10100 4
b10100 '
b10100 3
b10100 ;
b100 :
b1 7
b0 <
b1010 "
b1010 $
b1010 5
b1100 #
b1100 %
b1100 A
#25
0/
#30
b111100 !
b111100 &
b111100 4
b1000000000000 +
b1000000000000 1
b1000000000000 2
b111100 '
b111100 3
b111100 ;
b1100 *
b1100 0
b1100 =
b1100 B
b1100 :
b110 9
b11 7
b0 <
b110 (
b110 6
b110 @
b1100 )
b1100 >
b1100 ?
1/
#35
0/
#36
b1010100 !
b1010100 &
b1010100 4
b1010100 '
b1010100 3
b1010100 ;
b100 :
b101 7
b0 <
b1110 "
b1110 $
b1110 5
b1011 #
b1011 %
b1011 A
#40
b100000000000 +
b100000000000 1
b100000000000 2
b1011 *
b1011 0
b1011 =
b1011 B
b110 )
b110 >
b110 ?
1/
#45
0/
#50
b11000100 !
b11000100 &
b11000100 4
b11000100 '
b11000100 3
b11000100 ;
08
b100 :
b1110 9
b1100 7
b0 <
b1110 (
b1110 6
b1110 @
b1101 )
b1101 >
b1101 ?
1/
