Lab 1/4bitMagnitudeComparator/mag.v
module magnitudeComp4bit(opg,ope,opl,a,b);
	input [3:0] a,b;
	output opg,ope,opl;
	reg opg,ope,opl;
	always @ (a or b)
	begin
		 if(a > b)   begin  
            opl = 0;
            ope = 0;
            opg = 1;    end
        else if(a == b) begin 
            opl = 0;
            ope = 1;
            opg = 0;    end
        else    begin 
            opl = 1;
            ope = 0;
            opg =0;
        end 
	end
endmodule

Lab 1/4bitMagnitudeComparator/tb_mag.v
`include "mag.v"
module testbench;
	reg [3:0] a,b;
	wire opg,ope,opl;
	magnitudeComp4bit b1(opg,ope,opl,a,b);
	initial
		begin
			$dumpfile("output.vcd"); $dumpvars;
			$monitor(,$time," a=%b, b=%b,between a and b: equal=%b,less=%b,greater=%b",a,b,ope,opl,opg);
			#0 a=4'b0000;b=4'b0101;
			#5 a=4'b0001;
			#10 a=4'b0010;
			#15 a=4'b0011;
			#20 a=4'b0100;
			#25 a=4'b0101;
			#30 a=4'b0110;
			#35 a=4'b0111;
			#40 a=4'b1000;
			#45 a=4'b1001;
			#50 $finish;
		end
endmodule

Lab 1/4bitMagnitudeComparator/output.vcd
$date
	Thu Aug 27 16:13:33 2020
$end
$version
	Icarus Verilog
$end
$timescale
	1s
$end
$scope module testbench $end
$var wire 1 ! opl $end
$var wire 1 " opg $end
$var wire 1 # ope $end
$var reg 4 $ a [3:0] $end
$var reg 4 % b [3:0] $end
$scope module b1 $end
$var wire 4 & a [3:0] $end
$var wire 4 ' b [3:0] $end
$var reg 1 # ope $end
$var reg 1 " opg $end
$var reg 1 ! opl $end
$upscope $end
$upscope $end
$enddefinitions $end
#0
$dumpvars
b101 '
b0 &
b101 %
b0 $
0#
0"
1!
$end
#5
b1 $
b1 &
#15
b10 $
b10 &
#30
b11 $
b11 &
#50
b100 $
b100 &
#75
1#
0!
b101 $
b101 &
#105
1"
0#
b110 $
b110 &
#140
b111 $
b111 &
#180
b1000 $
b1000 &
#225
b1001 $
b1001 &
