Lab 2/mux16_1/mux4_1.v
module mux4_1(op,ip,s);
	output op;
	input [3:0] ip;
	input [1:0] s;
	assign op=(~s[0] & ~s[1] & ip[0])|(s[0] & ~s[1] & ip[1])|(~s[0] & s[1] & ip[2])|(s[0] & s[1] & ip[3]);
endmodule

Lab 2/mux4_1/tb_mux4_1.v
`include "mux4_1.v"
module testbench;
	reg [3:0] ip;
	reg [1:0] select;
	wire op;
	mux4_1 m1(op,ip,select);
	initial
		begin
			$dumpfile("mux4_1.vcd"); $dumpvars;
			$monitor(,$time," op =%b, select: %b, input: %b",op,select,ip);
			#0 ip=4'b0000;select=2'b00;
			#1 select=2'b01;
			#1 select=2'b10;
			#1 select=2'b11; 
			#5 ip=4'b0001;select=2'b00;
			#1 select=2'b01;
			#1 select=2'b10;
			#1 select=2'b11; 
			#5 ip=4'b0010;select=2'b00;
			#1 select=2'b01;
			#1 select=2'b10;
			#1 select=2'b11; 
		end
endmodule

Lab 2/mux4_1/mux4_1.vcd
$date
	Thu Sep 03 14:30:47 2020
$end
$version
	Icarus Verilog
$end
$timescale
	1s
$end
$scope module testbench $end
$var wire 1 ! op $end
$var reg 4 " ip [3:0] $end
$var reg 2 # select [1:0] $end
$scope module m1 $end
$var wire 4 $ ip [3:0] $end
$var wire 1 ! op $end
$var wire 2 % s [1:0] $end
$upscope $end
$upscope $end
$enddefinitions $end
#0
$dumpvars
b0 %
b0 $
b0 #
b0 "
0!
$end
#1
b1 #
b1 %
#2
b10 #
b10 %
#3
b11 #
b11 %
#8
1!
b0 #
b0 %
b1 "
b1 $
#9
0!
b1 #
b1 %
#10
b10 #
b10 %
#11
b11 #
b11 %
#16
b0 #
b0 %
b10 "
b10 $
#17
1!
b1 #
b1 %
#18
0!
b10 #
b10 %
#19
b11 #
b11 %
