Lab 1/BCD_to_Gray/bcd_to_gray.v
module bcd_to_gray(op,ip);
	input [3:0] ip;
	output [3:0] op;
	//Gate Level
	assign op[3]=ip[3];
	xor x1(op[2],ip[3],ip[2]);
	xor x2(op[1],ip[2],ip[1]);
	xor x3(op[0],ip[1],ip[0]);
	
	//Data Flow
	/*
		assign op[3]=ip[3];
		assign op[2]=ip[2]^ip[3];
		assign op[1]=ip[2]^ip[1];
		assign op[0]=ip[1]^ip[0];
	*/
endmodule

Lab 1/BCD_to_Gray/tb_bcd_to_gray.v
`include "bcd_to_gray.v"
module testbench;
	reg [3:0]ip;
	wire [3:0]op;
	bcd_to_gray b1(op,ip);
	initial
		begin
			$dumpfile("output.vcd"); $dumpvars;
			$monitor(,$time," ip=%b, op=%b",ip,op);
			#0 ip=4'b0000;
			#5 ip=4'b0001;
			#10 ip=4'b0010;
			#15 ip=4'b0011;
			#20 ip=4'b0100;
			#25 ip=4'b0101;
			#30 ip=4'b0110;
			#35 ip=4'b0111;
			#40 ip=4'b1000;
			#45 ip=4'b1001;
			#50 $finish;
		end
endmodule

Lab 1/BCD_to_Gray/output.vcd
$date
	Thu Aug 27 15:37:12 2020
$end
$version
	Icarus Verilog
$end
$timescale
	1s
$end
$scope module testbench $end
$var wire 4 ! op [3:0] $end
$var reg 4 " ip [3:0] $end
$scope module b1 $end
$var wire 4 # ip [3:0] $end
$var wire 4 $ op [3:0] $end
$upscope $end
$upscope $end
$enddefinitions $end
#0
$dumpvars
b0 $
b0 #
b0 "
b0 !
$end
#5
b1 !
b1 $
b1 "
b1 #
#15
b11 !
b11 $
b10 "
b10 #
#30
b10 !
b10 $
b11 "
b11 #
#50
b110 !
b110 $
b100 "
b100 #
#75
b111 !
b111 $
b101 "
b101 #
#105
b101 !
b101 $
b110 "
b110 #
#140
b100 !
b100 $
b111 "
b111 #
#180
b1100 !
b1100 $
b1000 "
b1000 #
#225
b1101 !
b1101 $
b1001 "
b1001 #
