Lab 1/1BitFullAdder/adder1bit.v
module adder1bit(sum,carry,a,b);
	input a,b;
	output sum,carry;
	assign sum=a^b;
	assign carry=a&b;
endmodule

Lab 3/shift register adder/fa1bit.v
`include "adder1bit.v"
module fulladder1bit(sum,cout,a,b,cin);
	input a,b,cin;
	output sum,cout;
	wire s,c;
	adder1bit half_adder(s,c,a,b);
	//s=a^b
	//c=a&b
	assign sum=s^cin;
	assign cout=cin&s|c;
endmodule

Lab 1/1BitFullAdder/tb_fulladder1bit.v
`include "fa1bit.v"
module testbench;
	reg a,b,cin;
	wire sum,carry;
	fulladder1bit a1(sum,carry,a,b,cin);
	initial
		begin
			$dumpfile("output.vcd"); $dumpvars;
			$monitor(,$time," a=%b, b=%b, cin=%b, sum=%b, carry=%b",a,b,cin,sum,carry);
			#0 a=1'b0;b=1'b0;cin=1'b0;
			#10 a=1'b0;b=1'b0;cin=1'b1;
			#20 a=1'b0;b=1'b1; cin=1'b0;
			#30 a=1'b0;b=1'b1;cin=1'b1;
			#40 a=1'b1;b=1'b0;cin=1'b0;
			#50 a=1'b1;b=1'b0;cin=1'b1;
			#60 a=1'b1;b=1'b1; cin=1'b0;
			#70 a=1'b1;b=1'b1;cin=1'b1;
			#80 $finish;
		end
endmodule

Lab 1/1BitFullAdder/output.vcd
$date
	Thu Aug 27 16:39:59 2020
$end
$version
	Icarus Verilog
$end
$timescale
	1s
$end
$scope module testbench $end
$var wire 1 ! sum $end
$var wire 1 " carry $end
$var reg 1 # a $end
$var reg 1 $ b $end
$var reg 1 % cin $end
$scope module a1 $end
$var wire 1 # a $end
$var wire 1 $ b $end
$var wire 1 % cin $end
$var wire 1 " cout $end
$var wire 1 ! sum $end
$var wire 1 & s $end
$var wire 1 ' c $end
$scope module half_adder $end
$var wire 1 # a $end
$var wire 1 $ b $end
$var wire 1 ' carry $end
$var wire 1 & sum $end
$upscope $end
$upscope $end
$upscope $end
$enddefinitions $end
#0
$dumpvars
0'
0&
0%
0$
0#
0"
0!
$end
#10
1!
1%
#30
1&
0%
1$
#60
1"
0!
1%
#100
0"
1!
0%
0$
1#
#150
1"
0!
1%
#210
0&
1'
0%
1$
#280
1!
1%
