Lab 6/aluControl.v
//ALU CONTROL
module aluControl(ALUOp1,ALUOp0,funct,operation);
	input ALUOp1,ALUOp0;
	input [5:0] funct;
	output [2:0] operation;
	wire w1;
	or o1(w1,funct[3],funct[0]);
	and a1(operation[0],ALUOp1,w1);
	and a2(w2,funct[1],ALUOp1);
	or o2(operation[2],ALUOp0,w2);
	nand n1(operation[1],ALUOp1,funct[2]);
endmodule

Lab 4/Control Unit/cu.v
module ANDarray (RegDst,ALUSrc, MemtoReg, RegWrite, MemRead, MemWrite,Branch,ALUOp0,ALUOp1,op);
input [5:0] op;
output RegDst,ALUSrc,MemtoReg, RegWrite, MemRead, MemWrite,Branch,ALUOp0,ALUOp1;
wire Rformat, lw,sw,beq;
assign Rformat= (~op[0])& (~op[1])& (~op[2])& (~op[3])& (~op[4])& (~op[5]);
assign lw= op[5]&(~op[4])&(~op[3])&(~op[2])&op[1]&op[0];
assign sw= op[5]&(~op[4])&(op[3])&(~op[2])&op[1]&op[0];
assign beq= (~op[5])&(~op[4])&(~op[3])&(op[2])&(~op[1])&(~op[0]);
assign RegDst=Rformat;
assign ALUSrc=lw|sw;
assign MemtoReg = lw;
assign RegWrite = Rformat|lw;
assign MemRead = lw;
assign MemWrite =sw;
assign Branch = beq;
assign ALUOp0 = Rformat;
assign ALUOp1 = beq;
endmodule

Lab 4/Control Unit/tb_aluControl.v
`include "cu.v"
`include "aluControl.v"
module testbench;
	reg [5:0] opcode,funct;
	integer i,j;
	wire RegDst,ALUSrc,MemtoReg, RegWrite, MemRead, MemWrite,Branch,ALUOp0,ALUOp1;
	wire [2:0] operation;
	ANDarray pla(RegDst,ALUSrc, MemtoReg, RegWrite, MemRead, MemWrite,Branch,ALUOp0,ALUOp1,opcode);
	aluControl aluc(ALUOp1,ALUOp0,funct,operation);
	initial begin
	$dumpfile("ALUcu.vcd"); $dumpvars;
	for( i = 0; i <= 63; i = i + 1)
	begin
	#100 opcode = i;
		for( j = 0; j <= 63; j = j + 1)
		begin
		#100 funct = j;
		$monitor("opcode = %b ",opcode,"funct = %b ",funct,"opeartion = %b ",operation,"ALUOp0 = %b ",ALUOp0,"ALUOp1 = %b ",ALUOp1);
		end
	end
	end
endmodule

Lab 4/Control Unit/ALUcu.vcd
$date
	Thu Sep 17 16:26:32 2020
$end
$version
	Icarus Verilog
$end
$timescale
	1s
$end
$scope module testbench $end
$var wire 3 ! operation [2:0] $end
$var wire 1 " RegWrite $end
$var wire 1 # RegDst $end
$var wire 1 $ MemtoReg $end
$var wire 1 % MemWrite $end
$var wire 1 & MemRead $end
$var wire 1 ' Branch $end
$var wire 1 ( ALUSrc $end
$var wire 1 ) ALUOp1 $end
$var wire 1 * ALUOp0 $end
$var reg 6 + funct [5:0] $end
$var reg 6 , opcode [5:0] $end
$var integer 32 - i [31:0] $end
$var integer 32 . j [31:0] $end
$scope module aluc $end
$var wire 6 / funct [5:0] $end
$var wire 1 0 w1 $end
$var wire 1 1 w2 $end
$var wire 3 2 operation [2:0] $end
$var wire 1 ) ALUOp1 $end
$var wire 1 * ALUOp0 $end
$upscope $end
$scope module pla $end
$var wire 1 * ALUOp0 $end
$var wire 1 ) ALUOp1 $end
$var wire 1 ( ALUSrc $end
$var wire 1 ' Branch $end
$var wire 1 & MemRead $end
$var wire 1 % MemWrite $end
$var wire 1 $ MemtoReg $end
$var wire 1 # RegDst $end
$var wire 1 " RegWrite $end
$var wire 1 3 Rformat $end
$var wire 1 4 beq $end
$var wire 1 5 lw $end
$var wire 6 6 op [5:0] $end
$var wire 1 7 sw $end
$upscope $end
$upscope $end
$enddefinitions $end
#0
$dumpvars
x7
bx 6
x5
x4
x3
bx 2
x1
x0
bx /
bx .
b0 -
bx ,
bx +
x*
x)
x(
x'
x&
x%
x$
x#
x"
bx !
$end
#100
1"
1#
1*
13
01
b110 !
b110 2
0'
0)
04
0(
0$
0&
05
0%
07
b0 .
b0 ,
b0 6
#200
00
b1 .
b0 +
b0 /
#300
10
b10 .
b1 +
b1 /
#400
00
b11 .
b10 +
b10 /
#500
10
b100 .
b11 +
b11 /
#600
00
b101 .
b100 +
b100 /
#700
10
b110 .
b101 +
b101 /
#800
00
b111 .
b110 +
b110 /
#900
10
b1000 .
b111 +
b111 /
#1000
b1001 .
b1000 +
b1000 /
#1100
b1010 .
b1001 +
b1001 /
#1200
b1011 .
b1010 +
b1010 /
#1300
b1100 .
b1011 +
b1011 /
#1400
b1101 .
b1100 +
b1100 /
#1500
b1110 .
b1101 +
b1101 /
#1600
b1111 .
b1110 +
b1110 /
#1700
b10000 .
b1111 +
b1111 /
#1800
00
b10001 .
b10000 +
b10000 /
#1900
10
b10010 .
b10001 +
b10001 /
#2000
00
b10011 .
b10010 +
b10010 /
#2100
10
b10100 .
b10011 +
b10011 /
#2200
00
b10101 .
b10100 +
b10100 /
#2300
10
b10110 .
b10101 +
b10101 /
#2400
00
b10111 .
b10110 +
b10110 /
#2500
10
b11000 .
b10111 +
b10111 /
#2600
b11001 .
b11000 +
b11000 /
#2700
b11010 .
b11001 +
b11001 /
#2800
b11011 .
b11010 +
b11010 /
#2900
b11100 .
b11011 +
b11011 /
#3000
b11101 .
b11100 +
b11100 /
#3100
b11110 .
b11101 +
b11101 /
#3200
b11111 .
b11110 +
b11110 /
#3300
b100000 .
b11111 +
b11111 /
#3400
00
b100001 .
b100000 +
b100000 /
#3500
10
b100010 .
b100001 +
b100001 /
#3600
00
b100011 .
b100010 +
b100010 /
#3700
10
b100100 .
b100011 +
b100011 /
#3800
00
b100101 .
b100100 +
b100100 /
#3900
10
b100110 .
b100101 +
b100101 /
#4000
00
b100111 .
b100110 +
b100110 /
#4100
10
b101000 .
b100111 +
b100111 /
#4200
b101001 .
b101000 +
b101000 /
#4300
b101010 .
b101001 +
b101001 /
#4400
b101011 .
b101010 +
b101010 /
#4500
b101100 .
b101011 +
b101011 /
#4600
b101101 .
b101100 +
b101100 /
#4700
b101110 .
b101101 +
b101101 /
#4800
b101111 .
b101110 +
b101110 /
#4900
b110000 .
b101111 +
b101111 /
#5000
00
b110001 .
b110000 +
b110000 /
#5100
10
b110010 .
b110001 +
b110001 /
#5200
00
b110011 .
b110010 +
b110010 /
#5300
10
b110100 .
b110011 +
b110011 /
#5400
00
b110101 .
b110100 +
b110100 /
#5500
10
b110110 .
b110101 +
b110101 /
#5600
00
b110111 .
b110110 +
b110110 /
#5700
10
b111000 .
b110111 +
b110111 /
#5800
b111001 .
b111000 +
b111000 /
#5900
b111010 .
b111001 +
b111001 /
#6000
b111011 .
b111010 +
b111010 /
#6100
b111100 .
b111011 +
b111011 /
#6200
b111101 .
b111100 +
b111100 /
#6300
b111110 .
b111101 +
b111101 /
#6400
b111111 .
b111110 +
b111110 /
#6500
b1 -
b1000000 .
b111111 +
b111111 /
#6600
0"
b10 !
b10 2
0#
0*
03
b0 .
b1 ,
b1 6
#6700
00
b1 .
b0 +
b0 /
#6800
10
b10 .
b1 +
b1 /
#6900
00
b11 .
b10 +
b10 /
#7000
10
b100 .
b11 +
b11 /
#7100
00
b101 .
b100 +
b100 /
#7200
10
b110 .
b101 +
b101 /
#7300
00
b111 .
b110 +
b110 /
#7400
10
b1000 .
b111 +
b111 /
#7500
b1001 .
b1000 +
b1000 /
#7600
b1010 .
b1001 +
b1001 /
#7700
b1011 .
b1010 +
b1010 /
#7800
b1100 .
b1011 +
b1011 /
#7900
b1101 .
b1100 +
b1100 /
#8000
b1110 .
b1101 +
b1101 /
#8100
b1111 .
b1110 +
b1110 /
#8200
b10000 .
b1111 +
b1111 /
#8300
00
b10001 .
b10000 +
b10000 /
#8400
10
b10010 .
b10001 +
b10001 /
#8500
00
b10011 .
b10010 +
b10010 /
#8600
10
b10100 .
b10011 +
b10011 /
#8700
00
b10101 .
b10100 +
b10100 /
#8800
10
b10110 .
b10101 +
b10101 /
#8900
00
b10111 .
b10110 +
b10110 /
#9000
10
b11000 .
b10111 +
b10111 /
#9100
b11001 .
b11000 +
b11000 /
#9200
b11010 .
b11001 +
b11001 /
#9300
b11011 .
b11010 +
b11010 /
#9400
b11100 .
b11011 +
b11011 /
#9500
b11101 .
b11100 +
b11100 /
#9600
b11110 .
b11101 +
b11101 /
#9700
b11111 .
b11110 +
b11110 /
#9800
b100000 .
b11111 +
b11111 /
#9900
00
b100001 .
b100000 +
b100000 /
#10000
10
b100010 .
b100001 +
b100001 /
#10100
00
b100011 .
b100010 +
b100010 /
#10200
10
b100100 .
b100011 +
b100011 /
#10300
00
b100101 .
b100100 +
b100100 /
#10400
10
b100110 .
b100101 +
b100101 /
#10500
00
b100111 .
b100110 +
b100110 /
#10600
10
b101000 .
b100111 +
b100111 /
#10700
b101001 .
b101000 +
b101000 /
#10800
b101010 .
b101001 +
b101001 /
#10900
b101011 .
b101010 +
b101010 /
#11000
b101100 .
b101011 +
b101011 /
#11100
b101101 .
b101100 +
b101100 /
#11200
b101110 .
b101101 +
b101101 /
#11300
b101111 .
b101110 +
b101110 /
#11400
b110000 .
b101111 +
b101111 /
#11500
00
b110001 .
b110000 +
b110000 /
#11600
10
b110010 .
b110001 +
b110001 /
#11700
00
b110011 .
b110010 +
b110010 /
#11800
10
b110100 .
b110011 +
b110011 /
#11900
00
b110101 .
b110100 +
b110100 /
#12000
10
b110110 .
b110101 +
b110101 /
#12100
00
b110111 .
b110110 +
b110110 /
#12200
10
b111000 .
b110111 +
b110111 /
#12300
b111001 .
b111000 +
b111000 /
#12400
b111010 .
b111001 +
b111001 /
#12500
b111011 .
b111010 +
b111010 /
#12600
b111100 .
b111011 +
b111011 /
#12700
b111101 .
b111100 +
b111100 /
#12800
b111110 .
b111101 +
b111101 /
#12900
b111111 .
b111110 +
b111110 /
#13000
b10 -
b1000000 .
b111111 +
b111111 /
#13100
b0 .
b10 ,
b10 6
#13200
00
b1 .
b0 +
b0 /
#13300
10
b10 .
b1 +
b1 /
#13400
00
b11 .
b10 +
b10 /
#13500
10
b100 .
b11 +
b11 /
#13600
00
b101 .
b100 +
b100 /
#13700
10
b110 .
b101 +
b101 /
#13800
00
b111 .
b110 +
b110 /
#13900
10
b1000 .
b111 +
b111 /
#14000
b1001 .
b1000 +
b1000 /
#14100
b1010 .
b1001 +
b1001 /
#14200
b1011 .
b1010 +
b1010 /
#14300
b1100 .
b1011 +
b1011 /
#14400
b1101 .
b1100 +
b1100 /
#14500
b1110 .
b1101 +
b1101 /
#14600
b1111 .
b1110 +
b1110 /
#14700
b10000 .
b1111 +
b1111 /
#14800
00
b10001 .
b10000 +
b10000 /
#14900
10
b10010 .
b10001 +
b10001 /
#15000
00
b10011 .
b10010 +
b10010 /
#15100
10
b10100 .
b10011 +
b10011 /
#15200
00
b10101 .
b10100 +
b10100 /
#15300
10
b10110 .
b10101 +
b10101 /
#15400
00
b10111 .
b10110 +
b10110 /
#15500
10
b11000 .
b10111 +
b10111 /
#15600
b11001 .
b11000 +
b11000 /
#15700
b11010 .
b11001 +
b11001 /
#15800
b11011 .
b11010 +
b11010 /
#15900
b11100 .
b11011 +
b11011 /
#16000
b11101 .
b11100 +
b11100 /
#16100
b11110 .
b11101 +
b11101 /
#16200
b11111 .
b11110 +
b11110 /
#16300
b100000 .
b11111 +
b11111 /
#16400
00
b100001 .
b100000 +
b100000 /
#16500
10
b100010 .
b100001 +
b100001 /
#16600
00
b100011 .
b100010 +
b100010 /
#16700
10
b100100 .
b100011 +
b100011 /
#16800
00
b100101 .
b100100 +
b100100 /
#16900
10
b100110 .
b100101 +
b100101 /
#17000
00
b100111 .
b100110 +
b100110 /
#17100
10
b101000 .
b100111 +
b100111 /
#17200
b101001 .
b101000 +
b101000 /
#17300
b101010 .
b101001 +
b101001 /
#17400
b101011 .
b101010 +
b101010 /
#17500
b101100 .
b101011 +
b101011 /
#17600
b101101 .
b101100 +
b101100 /
#17700
b101110 .
b101101 +
b101101 /
#17800
b101111 .
b101110 +
b101110 /
#17900
b110000 .
b101111 +
b101111 /
#18000
00
b110001 .
b110000 +
b110000 /
#18100
10
b110010 .
b110001 +
b110001 /
#18200
00
b110011 .
b110010 +
b110010 /
#18300
10
b110100 .
b110011 +
b110011 /
#18400
00
b110101 .
b110100 +
b110100 /
#18500
10
b110110 .
b110101 +
b110101 /
#18600
00
b110111 .
b110110 +
b110110 /
#18700
10
b111000 .
b110111 +
b110111 /
#18800
b111001 .
b111000 +
b111000 /
#18900
b111010 .
b111001 +
b111001 /
#19000
b111011 .
b111010 +
b111010 /
#19100
b111100 .
b111011 +
b111011 /
#19200
b111101 .
b111100 +
b111100 /
#19300
b111110 .
b111101 +
b111101 /
#19400
b111111 .
b111110 +
b111110 /
#19500
b11 -
b1000000 .
b111111 +
b111111 /
#19600
b0 .
b11 ,
b11 6
#19700
00
b1 .
b0 +
b0 /
#19800
10
b10 .
b1 +
b1 /
#19900
00
b11 .
b10 +
b10 /
#20000
10
b100 .
b11 +
b11 /
#20100
00
b101 .
b100 +
b100 /
#20200
10
b110 .
b101 +
b101 /
#20300
00
b111 .
b110 +
b110 /
#20400
10
b1000 .
b111 +
b111 /
#20500
b1001 .
b1000 +
b1000 /
#20600
b1010 .
b1001 +
b1001 /
#20700
b1011 .
b1010 +
b1010 /
#20800
b1100 .
b1011 +
b1011 /
#20900
b1101 .
b1100 +
b1100 /
#21000
b1110 .
b1101 +
b1101 /
#21100
b1111 .
b1110 +
b1110 /
#21200
b10000 .
b1111 +
b1111 /
#21300
00
b10001 .
b10000 +
b10000 /
#21400
10
b10010 .
b10001 +
b10001 /
#21500
00
b10011 .
b10010 +
b10010 /
#21600
10
b10100 .
b10011 +
b10011 /
#21700
00
b10101 .
b10100 +
b10100 /
#21800
10
b10110 .
b10101 +
b10101 /
#21900
00
b10111 .
b10110 +
b10110 /
#22000
10
b11000 .
b10111 +
b10111 /
#22100
b11001 .
b11000 +
b11000 /
#22200
b11010 .
b11001 +
b11001 /
#22300
b11011 .
b11010 +
b11010 /
#22400
b11100 .
b11011 +
b11011 /
#22500
b11101 .
b11100 +
b11100 /
#22600
b11110 .
b11101 +
b11101 /
#22700
b11111 .
b11110 +
b11110 /
#22800
b100000 .
b11111 +
b11111 /
#22900
00
b100001 .
b100000 +
b100000 /
#23000
10
b100010 .
b100001 +
b100001 /
#23100
00
b100011 .
b100010 +
b100010 /
#23200
10
b100100 .
b100011 +
b100011 /
#23300
00
b100101 .
b100100 +
b100100 /
#23400
10
b100110 .
b100101 +
b100101 /
#23500
00
b100111 .
b100110 +
b100110 /
#23600
10
b101000 .
b100111 +
b100111 /
#23700
b101001 .
b101000 +
b101000 /
#23800
b101010 .
b101001 +
b101001 /
#23900
b101011 .
b101010 +
b101010 /
#24000
b101100 .
b101011 +
b101011 /
#24100
b101101 .
b101100 +
b101100 /
#24200
b101110 .
b101101 +
b101101 /
#24300
b101111 .
b101110 +
b101110 /
#24400
b110000 .
b101111 +
b101111 /
#24500
00
b110001 .
b110000 +
b110000 /
#24600
10
b110010 .
b110001 +
b110001 /
#24700
00
b110011 .
b110010 +
b110010 /
#24800
10
b110100 .
b110011 +
b110011 /
#24900
00
b110101 .
b110100 +
b110100 /
#25000
10
b110110 .
b110101 +
b110101 /
#25100
00
b110111 .
b110110 +
b110110 /
#25200
10
b111000 .
b110111 +
b110111 /
#25300
b111001 .
b111000 +
b111000 /
#25400
b111010 .
b111001 +
b111001 /
#25500
b111011 .
b111010 +
b111010 /
#25600
b111100 .
b111011 +
b111011 /
#25700
b111101 .
b111100 +
b111100 /
#25800
b111110 .
b111101 +
b111101 /
#25900
b111111 .
b111110 +
b111110 /
#26000
b100 -
b1000000 .
b111111 +
b111111 /
#26100
11
b101 !
b101 2
1'
1)
14
b0 .
b100 ,
b100 6
#26200
00
01
b10 !
b10 2
b1 .
b0 +
b0 /
#26300
b11 !
b11 2
10
b10 .
b1 +
b1 /
#26400
b110 !
b110 2
00
11
b11 .
b10 +
b10 /
#26500
b111 !
b111 2
10
b100 .
b11 +
b11 /
#26600
00
01
b0 !
b0 2
b101 .
b100 +
b100 /
#26700
b1 !
b1 2
10
b110 .
b101 +
b101 /
#26800
b100 !
b100 2
00
11
b111 .
b110 +
b110 /
#26900
b101 !
b101 2
10
b1000 .
b111 +
b111 /
#27000
01
b11 !
b11 2
b1001 .
b1000 +
b1000 /
#27100
b1010 .
b1001 +
b1001 /
#27200
b111 !
b111 2
11
b1011 .
b1010 +
b1010 /
#27300
b1100 .
b1011 +
b1011 /
#27400
01
b1 !
b1 2
b1101 .
b1100 +
b1100 /
#27500
b1110 .
b1101 +
b1101 /
#27600
b101 !
b101 2
11
b1111 .
b1110 +
b1110 /
#27700
b10000 .
b1111 +
b1111 /
#27800
00
01
b10 !
b10 2
b10001 .
b10000 +
b10000 /
#27900
b11 !
b11 2
10
b10010 .
b10001 +
b10001 /
#28000
b110 !
b110 2
00
11
b10011 .
b10010 +
b10010 /
#28100
b111 !
b111 2
10
b10100 .
b10011 +
b10011 /
#28200
00
01
b0 !
b0 2
b10101 .
b10100 +
b10100 /
#28300
b1 !
b1 2
10
b10110 .
b10101 +
b10101 /
#28400
b100 !
b100 2
00
11
b10111 .
b10110 +
b10110 /
#28500
b101 !
b101 2
10
b11000 .
b10111 +
b10111 /
#28600
01
b11 !
b11 2
b11001 .
b11000 +
b11000 /
#28700
b11010 .
b11001 +
b11001 /
#28800
b111 !
b111 2
11
b11011 .
b11010 +
b11010 /
#28900
b11100 .
b11011 +
b11011 /
#29000
01
b1 !
b1 2
b11101 .
b11100 +
b11100 /
#29100
b11110 .
b11101 +
b11101 /
#29200
b101 !
b101 2
11
b11111 .
b11110 +
b11110 /
#29300
b100000 .
b11111 +
b11111 /
#29400
00
01
b10 !
b10 2
b100001 .
b100000 +
b100000 /
#29500
b11 !
b11 2
10
b100010 .
b100001 +
b100001 /
#29600
b110 !
b110 2
00
11
b100011 .
b100010 +
b100010 /
#29700
b111 !
b111 2
10
b100100 .
b100011 +
b100011 /
#29800
00
01
b0 !
b0 2
b100101 .
b100100 +
b100100 /
#29900
b1 !
b1 2
10
b100110 .
b100101 +
b100101 /
#30000
b100 !
b100 2
00
11
b100111 .
b100110 +
b100110 /
#30100
b101 !
b101 2
10
b101000 .
b100111 +
b100111 /
#30200
01
b11 !
b11 2
b101001 .
b101000 +
b101000 /
#30300
b101010 .
b101001 +
b101001 /
#30400
b111 !
b111 2
11
b101011 .
b101010 +
b101010 /
#30500
b101100 .
b101011 +
b101011 /
#30600
01
b1 !
b1 2
b101101 .
b101100 +
b101100 /
#30700
b101110 .
b101101 +
b101101 /
#30800
b101 !
b101 2
11
b101111 .
b101110 +
b101110 /
#30900
b110000 .
b101111 +
b101111 /
#31000
00
01
b10 !
b10 2
b110001 .
b110000 +
b110000 /
#31100
b11 !
b11 2
10
b110010 .
b110001 +
b110001 /
#31200
b110 !
b110 2
00
11
b110011 .
b110010 +
b110010 /
#31300
b111 !
b111 2
10
b110100 .
b110011 +
b110011 /
#31400
00
01
b0 !
b0 2
b110101 .
b110100 +
b110100 /
#31500
b1 !
b1 2
10
b110110 .
b110101 +
b110101 /
#31600
b100 !
b100 2
00
11
b110111 .
b110110 +
b110110 /
#31700
b101 !
b101 2
10
b111000 .
b110111 +
b110111 /
#31800
01
b11 !
b11 2
b111001 .
b111000 +
b111000 /
#31900
b111010 .
b111001 +
b111001 /
#32000
b111 !
b111 2
11
b111011 .
b111010 +
b111010 /
#32100
b111100 .
b111011 +
b111011 /
#32200
01
b1 !
b1 2
b111101 .
b111100 +
b111100 /
#32300
b111110 .
b111101 +
b111101 /
#32400
b101 !
b101 2
11
b111111 .
b111110 +
b111110 /
#32500
b101 -
b1000000 .
b111111 +
b111111 /
#32600
01
b10 !
b10 2
0'
0)
04
b0 .
b101 ,
b101 6
#32700
00
b1 .
b0 +
b0 /
#32800
10
b10 .
b1 +
b1 /
#32900
00
b11 .
b10 +
b10 /
#33000
10
b100 .
b11 +
b11 /
#33100
00
b101 .
b100 +
b100 /
#33200
10
b110 .
b101 +
b101 /
#33300
00
b111 .
b110 +
b110 /
#33400
10
b1000 .
b111 +
b111 /
#33500
b1001 .
b1000 +
b1000 /
#33600
b1010 .
b1001 +
b1001 /
#33700
b1011 .
b1010 +
b1010 /
#33800
b1100 .
b1011 +
b1011 /
#33900
b1101 .
b1100 +
b1100 /
#34000
b1110 .
b1101 +
b1101 /
#34100
b1111 .
b1110 +
b1110 /
#34200
b10000 .
b1111 +
b1111 /
#34300
00
b10001 .
b10000 +
b10000 /
#34400
10
b10010 .
b10001 +
b10001 /
#34500
00
b10011 .
b10010 +
b10010 /
#34600
10
b10100 .
b10011 +
b10011 /
#34700
00
b10101 .
b10100 +
b10100 /
#34800
10
b10110 .
b10101 +
b10101 /
#34900
00
b10111 .
b10110 +
b10110 /
#35000
10
b11000 .
b10111 +
b10111 /
#35100
b11001 .
b11000 +
b11000 /
#35200
b11010 .
b11001 +
b11001 /
#35300
b11011 .
b11010 +
b11010 /
#35400
b11100 .
b11011 +
b11011 /
#35500
b11101 .
b11100 +
b11100 /
#35600
b11110 .
b11101 +
b11101 /
#35700
b11111 .
b11110 +
b11110 /
#35800
b100000 .
b11111 +
b11111 /
#35900
00
b100001 .
b100000 +
b100000 /
#36000
10
b100010 .
b100001 +
b100001 /
#36100
00
b100011 .
b100010 +
b100010 /
#36200
10
b100100 .
b100011 +
b100011 /
#36300
00
b100101 .
b100100 +
b100100 /
#36400
10
b100110 .
b100101 +
b100101 /
#36500
00
b100111 .
b100110 +
b100110 /
#36600
10
b101000 .
b100111 +
b100111 /
#36700
b101001 .
b101000 +
b101000 /
#36800
b101010 .
b101001 +
b101001 /
#36900
b101011 .
b101010 +
b101010 /
#37000
b101100 .
b101011 +
b101011 /
#37100
b101101 .
b101100 +
b101100 /
#37200
b101110 .
b101101 +
b101101 /
#37300
b101111 .
b101110 +
b101110 /
#37400
b110000 .
b101111 +
b101111 /
#37500
00
b110001 .
b110000 +
b110000 /
#37600
10
b110010 .
b110001 +
b110001 /
#37700
00
b110011 .
b110010 +
b110010 /
#37800
10
b110100 .
b110011 +
b110011 /
#37900
00
b110101 .
b110100 +
b110100 /
#38000
10
b110110 .
b110101 +
b110101 /
#38100
00
b110111 .
b110110 +
b110110 /
#38200
10
b111000 .
b110111 +
b110111 /
#38300
b111001 .
b111000 +
b111000 /
#38400
b111010 .
b111001 +
b111001 /
#38500
b111011 .
b111010 +
b111010 /
#38600
b111100 .
b111011 +
b111011 /
#38700
b111101 .
b111100 +
b111100 /
#38800
b111110 .
b111101 +
b111101 /
#38900
b111111 .
b111110 +
b111110 /
#39000
b110 -
b1000000 .
b111111 +
b111111 /
#39100
01
b10 !
b10 2
0'
0)
04
b0 .
b110 ,
b110 6
#39200
00
b1 .
b0 +
b0 /
#39300
10
b10 .
b1 +
b1 /
#39400
00
b11 .
b10 +
b10 /
#39500
10
b100 .
b11 +
b11 /
#39600
00
b101 .
b100 +
b100 /
#39700
10
b110 .
b101 +
b101 /
#39800
00
b111 .
b110 +
b110 /
#39900
10
b1000 .
b111 +
b111 /
#40000
b1001 .
b1000 +
b1000 /
#40100
b1010 .
b1001 +
b1001 /
#40200
b1011 .
b1010 +
b1010 /
#40300
b1100 .
b1011 +
b1011 /
#40400
b1101 .
b1100 +
b1100 /
#40500
b1110 .
b1101 +
b1101 /
#40600
b1111 .
b1110 +
b1110 /
#40700
b10000 .
b1111 +
b1111 /
#40800
00
b10001 .
b10000 +
b10000 /
#40900
10
b10010 .
b10001 +
b10001 /
#41000
00
b10011 .
b10010 +
b10010 /
#41100
10
b10100 .
b10011 +
b10011 /
#41200
00
b10101 .
b10100 +
b10100 /
#41300
10
b10110 .
b10101 +
b10101 /
#41400
00
b10111 .
b10110 +
b10110 /
#41500
10
b11000 .
b10111 +
b10111 /
#41600
b11001 .
b11000 +
b11000 /
#41700
b11010 .
b11001 +
b11001 /
#41800
b11011 .
b11010 +
b11010 /
#41900
b11100 .
b11011 +
b11011 /
#42000
b11101 .
b11100 +
b11100 /
#42100
b11110 .
b11101 +
b11101 /
#42200
b11111 .
b11110 +
b11110 /
#42300
b100000 .
b11111 +
b11111 /
#42400
00
b100001 .
b100000 +
b100000 /
#42500
10
b100010 .
b100001 +
b100001 /
#42600
00
b100011 .
b100010 +
b100010 /
#42700
10
b100100 .
b100011 +
b100011 /
#42800
00
b100101 .
b100100 +
b100100 /
#42900
10
b100110 .
b100101 +
b100101 /
#43000
00
b100111 .
b100110 +
b100110 /
#43100
10
b101000 .
b100111 +
b100111 /
#43200
b101001 .
b101000 +
b101000 /
#43300
b101010 .
b101001 +
b101001 /
#43400
b101011 .
b101010 +
b101010 /
#43500
b101100 .
b101011 +
b101011 /
#43600
b101101 .
b101100 +
b101100 /
#43700
b101110 .
b101101 +
b101101 /
#43800
b101111 .
b101110 +
b101110 /
#43900
b110000 .
b101111 +
b101111 /
#44000
00
b110001 .
b110000 +
b110000 /
#44100
10
b110010 .
b110001 +
b110001 /
#44200
00
b110011 .
b110010 +
b110010 /
#44300
10
b110100 .
b110011 +
b110011 /
#44400
00
b110101 .
b110100 +
b110100 /
#44500
10
b110110 .
b110101 +
b110101 /
#44600
00
b110111 .
b110110 +
b110110 /
#44700
10
b111000 .
b110111 +
b110111 /
#44800
b111001 .
b111000 +
b111000 /
#44900
b111010 .
b111001 +
b111001 /
#45000
b111011 .
b111010 +
b111010 /
#45100
b111100 .
b111011 +
b111011 /
#45200
b111101 .
b111100 +
b111100 /
#45300
b111110 .
b111101 +
b111101 /
#45400
b111111 .
b111110 +
b111110 /
#45500
b111 -
b1000000 .
b111111 +
b111111 /
#45600
b0 .
b111 ,
b111 6
#45700
00
b1 .
b0 +
b0 /
#45800
10
b10 .
b1 +
b1 /
#45900
00
b11 .
b10 +
b10 /
#46000
10
b100 .
b11 +
b11 /
#46100
00
b101 .
b100 +
b100 /
#46200
10
b110 .
b101 +
b101 /
#46300
00
b111 .
b110 +
b110 /
#46400
10
b1000 .
b111 +
b111 /
#46500
b1001 .
b1000 +
b1000 /
#46600
b1010 .
b1001 +
b1001 /
#46700
b1011 .
b1010 +
b1010 /
#46800
b1100 .
b1011 +
b1011 /
#46900
b1101 .
b1100 +
b1100 /
#47000
b1110 .
b1101 +
b1101 /
#47100
b1111 .
b1110 +
b1110 /
#47200
b10000 .
b1111 +
b1111 /
#47300
00
b10001 .
b10000 +
b10000 /
#47400
10
b10010 .
b10001 +
b10001 /
#47500
00
b10011 .
b10010 +
b10010 /
#47600
10
b10100 .
b10011 +
b10011 /
#47700
00
b10101 .
b10100 +
b10100 /
#47800
10
b10110 .
b10101 +
b10101 /
#47900
00
b10111 .
b10110 +
b10110 /
#48000
10
b11000 .
b10111 +
b10111 /
#48100
b11001 .
b11000 +
b11000 /
#48200
b11010 .
b11001 +
b11001 /
#48300
b11011 .
b11010 +
b11010 /
#48400
b11100 .
b11011 +
b11011 /
#48500
b11101 .
b11100 +
b11100 /
#48600
b11110 .
b11101 +
b11101 /
#48700
b11111 .
b11110 +
b11110 /
#48800
b100000 .
b11111 +
b11111 /
#48900
00
b100001 .
b100000 +
b100000 /
#49000
10
b100010 .
b100001 +
b100001 /
#49100
00
b100011 .
b100010 +
b100010 /
#49200
10
b100100 .
b100011 +
b100011 /
#49300
00
b100101 .
b100100 +
b100100 /
#49400
10
b100110 .
b100101 +
b100101 /
#49500
00
b100111 .
b100110 +
b100110 /
#49600
10
b101000 .
b100111 +
b100111 /
#49700
b101001 .
b101000 +
b101000 /
#49800
b101010 .
b101001 +
b101001 /
#49900
b101011 .
b101010 +
b101010 /
#50000
b101100 .
b101011 +
b101011 /
#50100
b101101 .
b101100 +
b101100 /
#50200
b101110 .
b101101 +
b101101 /
#50300
b101111 .
b101110 +
b101110 /
#50400
b110000 .
b101111 +
b101111 /
#50500
00
b110001 .
b110000 +
b110000 /
#50600
10
b110010 .
b110001 +
b110001 /
#50700
00
b110011 .
b110010 +
b110010 /
#50800
10
b110100 .
b110011 +
b110011 /
#50900
00
b110101 .
b110100 +
b110100 /
#51000
10
b110110 .
b110101 +
b110101 /
#51100
00
b110111 .
b110110 +
b110110 /
#51200
10
b111000 .
b110111 +
b110111 /
#51300
b111001 .
b111000 +
b111000 /
#51400
b111010 .
b111001 +
b111001 /
#51500
b111011 .
b111010 +
b111010 /
#51600
b111100 .
b111011 +
b111011 /
#51700
b111101 .
b111100 +
b111100 /
#51800
b111110 .
b111101 +
b111101 /
#51900
b111111 .
b111110 +
b111110 /
#52000
b1000 -
b1000000 .
b111111 +
b111111 /
#52100
b0 .
b1000 ,
b1000 6
#52200
00
b1 .
b0 +
b0 /
#52300
10
b10 .
b1 +
b1 /
#52400
00
b11 .
b10 +
b10 /
#52500
10
b100 .
b11 +
b11 /
#52600
00
b101 .
b100 +
b100 /
#52700
10
b110 .
b101 +
b101 /
#52800
00
b111 .
b110 +
b110 /
#52900
10
b1000 .
b111 +
b111 /
#53000
b1001 .
b1000 +
b1000 /
#53100
b1010 .
b1001 +
b1001 /
#53200
b1011 .
b1010 +
b1010 /
#53300
b1100 .
b1011 +
b1011 /
#53400
b1101 .
b1100 +
b1100 /
#53500
b1110 .
b1101 +
b1101 /
#53600
b1111 .
b1110 +
b1110 /
#53700
b10000 .
b1111 +
b1111 /
#53800
00
b10001 .
b10000 +
b10000 /
#53900
10
b10010 .
b10001 +
b10001 /
#54000
00
b10011 .
b10010 +
b10010 /
#54100
10
b10100 .
b10011 +
b10011 /
#54200
00
b10101 .
b10100 +
b10100 /
#54300
10
b10110 .
b10101 +
b10101 /
#54400
00
b10111 .
b10110 +
b10110 /
#54500
10
b11000 .
b10111 +
b10111 /
#54600
b11001 .
b11000 +
b11000 /
#54700
b11010 .
b11001 +
b11001 /
